shweatherpredict/__init__.py
shweatherpredict/shsolarpredict.py
shweatherpredict/shsql.py
shweatherpredict/shweatherpredict.py
sh_weather_predict-1.0.0.5.dist-info/METADATA
sh_weather_predict-1.0.0.5.dist-info/WHEEL
sh_weather_predict-1.0.0.5.dist-info/top_level.txt
sh_weather_predict-1.0.0.5.dist-info/RECORD
